autonode_diagrams/__init__.py
autonode_diagrams/icon.py
autonode_diagrams-1.0.4.dist-info/LICENSE
autonode_diagrams-1.0.4.dist-info/WHEEL
autonode_diagrams-1.0.4.dist-info/METADATA
autonode_diagrams-1.0.4.dist-info/RECORD
