Metadata-Version: 2.1
Name: autonode-diagrams
Version: 1.0.4
Summary: Automatically generate node icons for Python Diagrams based on label text
Author: Ryan McKeown
Author-email: ryanmckeown@mail4me.com
Requires-Python: >=3.7,<4.0
Classifier: License :: OSI Approved :: GNU General Public License v3 (GPLv3)
Classifier: Operating System :: OS Independent
Classifier: Programming Language :: Python :: 3
Classifier: Programming Language :: Python :: 3.7
Classifier: Programming Language :: Python :: 3.8
Classifier: Programming Language :: Python :: 3.9
Classifier: Programming Language :: Python :: 3.10
Classifier: Programming Language :: Python :: 3.11
Classifier: Programming Language :: Python :: 3
Requires-Dist: diagrams (>=0.6.0)
Requires-Dist: pillow (>=9.2.0)
